forexcast.py
forexcast-0.1.0.dist-info/LICENSE
forexcast-0.1.0.dist-info/METADATA
forexcast-0.1.0.dist-info/WHEEL
forexcast-0.1.0.dist-info/entry_points.txt
forexcast-0.1.0.dist-info/top_level.txt
forexcast-0.1.0.dist-info/RECORD
