Metadata-Version: 2.1
Name: forexcast
Version: 0.1.0
Summary: Simple currency forecasting for IEX data
Home-page: https://github.com/IntrospectData/forexcast
Author: Bradley Reimers
Author-email: b.a.reimers@gmail.com
License: MIT
Download-URL: https://github.com/IntrospectData/forexcast/archive/v0.1.0.tar.gz
Keywords: forecast,finance,fintech,currency,fbprophet
Platform: UNKNOWN
Classifier: Development Status :: 3 - Alpha
Classifier: Intended Audience :: Financial and Insurance Industry
Classifier: Topic :: Office/Business :: Financial :: Investment
Classifier: License :: OSI Approved :: MIT License
Classifier: Programming Language :: Python :: 3
Classifier: Programming Language :: Python :: 3.7
Requires-Dist: Click
Requires-Dist: fbprophet
Requires-Dist: holidays (<=0.10)
Requires-Dist: pandas
Requires-Dist: requests
Requires-Dist: plotly
